triple_quote/__init__.py
triple_quote/triple_quote.py
triple_quote-0.1.3.dist-info/METADATA
triple_quote-0.1.3.dist-info/WHEEL
triple_quote-0.1.3.dist-info/entry_points.txt
triple_quote-0.1.3.dist-info/RECORD
