Metadata-Version: 2.1
Name: triple-quote
Version: 0.1.3
Summary: Format line inside of triple quotes to PEP8
Author: jpstudioweb
Author-email: jpaulo6ba@gmail.com
Requires-Python: >=3.12,<4.0
Classifier: Programming Language :: Python :: 3
Classifier: Programming Language :: Python :: 3.12
